{"faceAnnotations":[],"landmarkAnnotations":[],"logoAnnotations":[],"labelAnnotations":[],"textAnnotations":[{"locations":[],"properties":[],"mid":"","locale":"pl","description":"SAUF &\nod 0000\n","score":0,"confidence":0,"topicality":0,"boundingPoly":{"vertices":[{"x":2,"y":525},{"x":881,"y":525},{"x":881,"y":1097},{"x":2,"y":1097}],"normalizedVertices":[]}},{"locations":[],"properties":[],"mid":"","locale":"","description":"SAUF","score":0,"confidence":0,"topicality":0,"boundingPoly":{"vertices":[{"x":621,"y":525},{"x":808,"y":529},{"x":806,"y":610},{"x":619,"y":606}],"normalizedVertices":[]}},{"locations":[],"properties":[],"mid":"","locale":"","description":"&","score":0,"confidence":0,"topicality":0,"boundingPoly":{"vertices":[{"x":858,"y":530},{"x":881,"y":531},{"x":879,"y":611},{"x":856,"y":611}],"normalizedVertices":[]}},{"locations":[],"properties":[],"mid":"","locale":"","description":"od","score":0,"confidence":0,"topicality":0,"boundingPoly":{"vertices":[{"x":2,"y":1076},{"x":34,"y":1076},{"x":34,"y":1097},{"x":2,"y":1097}],"normalizedVertices":[]}},{"locations":[],"properties":[],"mid":"","locale":"","description":"0000","score":0,"confidence":0,"topicality":0,"boundingPoly":{"vertices":[{"x":43,"y":1076},{"x":107,"y":1076},{"x":107,"y":1097},{"x":43,"y":1097}],"normalizedVertices":[]}}],"localizedObjectAnnotations":[{"mid":"/m/0d4v4","languageCode":"","name":"Window","score":0.6210055947303772,"boundingPoly":{"vertices":[],"normalizedVertices":[{"x":0.877047598361969,"y":0.340677946805954},{"x":0.9932929277420044,"y":0.340677946805954},{"x":0.9932929277420044,"y":0.6757926344871521},{"x":0.877047598361969,"y":0.6757926344871521}]}},{"mid":"/m/01mqdt","languageCode":"","name":"Traffic sign","score":0.5591258406639099,"boundingPoly":{"vertices":[],"normalizedVertices":[{"x":0.3611764907836914,"y":0.0040000006556510925},{"x":0.6908235549926758,"y":0.0040000006556510925},{"x":0.6908235549926758,"y":0.2437647134065628},{"x":0.3611764907836914,"y":0.2437647134065628}]}}],"safeSearchAnnotation":null,"imagePropertiesAnnotation":{"dominantColors":{"colors":[{"color":{"red":234,"green":227,"blue":217,"alpha":null},"score":0.34689733386039734,"pixelFraction":0.24525073170661926},{"color":{"red":50,"green":47,"blue":45,"alpha":null},"score":0.07465801388025284,"pixelFraction":0.2457227110862732},{"color":{"red":183,"green":69,"blue":85,"alpha":null},"score":0.04740418121218681,"pixelFraction":0.005958701949566603},{"color":{"red":33,"green":93,"blue":147,"alpha":null},"score":0.03361321985721588,"pixelFraction":0.006135693285614252},{"color":{"red":16,"green":92,"blue":180,"alpha":null},"score":0.025235846638679504,"pixelFraction":0.0029498524963855743},{"color":{"red":206,"green":202,"blue":193,"alpha":null},"score":0.07847128808498383,"pixelFraction":0.10306784510612488},{"color":{"red":26,"green":23,"blue":21,"alpha":null},"score":0.0725456178188324,"pixelFraction":0.052625369280576706},{"color":{"red":170,"green":78,"blue":82,"alpha":null},"score":0.03190833330154419,"pixelFraction":0.004601770080626011},{"color":{"red":232,"green":225,"blue":207,"alpha":null},"score":0.031083520501852036,"pixelFraction":0.030029498040676117},{"color":{"red":160,"green":157,"blue":151,"alpha":null},"score":0.028231315314769745,"pixelFraction":0.1787610650062561}]}},"error":null,"cropHintsAnnotation":{"cropHints":[{"boundingPoly":{"vertices":[{"x":0,"y":0},{"x":1499,"y":0},{"x":1499,"y":1999},{"x":0,"y":1999}],"normalizedVertices":[]},"confidence":0.7999999523162842,"importanceFraction":1}]},"fullTextAnnotation":{"pages":[{"blocks":[{"paragraphs":[{"words":[{"symbols":[{"property":{"detectedLanguages":[{"languageCode":"fr","confidence":0}],"detectedBreak":null},"boundingBox":{"vertices":[{"x":619,"y":525},{"x":661,"y":525},{"x":661,"y":607},{"x":619,"y":607}],"normalizedVertices":[]},"text":"S","confidence":0.9900000095367432},{"property":{"detectedLanguages":[{"languageCode":"fr","confidence":0}],"detectedBreak":null},"boundingBox":{"vertices":[{"x":668,"y":525},{"x":710,"y":525},{"x":710,"y":607},{"x":668,"y":607}],"normalizedVertices":[]},"text":"A","confidence":0.9900000095367432},{"property":{"detectedLanguages":[{"languageCode":"fr","confidence":0}],"detectedBreak":null},"boundingBox":{"vertices":[{"x":717,"y":527},{"x":759,"y":527},{"x":759,"y":609},{"x":717,"y":609}],"normalizedVertices":[]},"text":"U","confidence":0.9900000095367432},{"property":{"detectedLanguages":[{"languageCode":"fr","confidence":0}],"detectedBreak":{"type":"SPACE","isPrefix":false}},"boundingBox":{"vertices":[{"x":766,"y":528},{"x":808,"y":528},{"x":808,"y":610},{"x":766,"y":610}],"normalizedVertices":[]},"text":"F","confidence":0.9900000095367432}],"property":{"detectedLanguages":[{"languageCode":"fr","confidence":0}],"detectedBreak":null},"boundingBox":{"vertices":[{"x":621,"y":525},{"x":808,"y":529},{"x":806,"y":610},{"x":619,"y":606}],"normalizedVertices":[]},"confidence":0.9900000095367432},{"symbols":[{"property":{"detectedLanguages":[{"languageCode":"fr","confidence":0}],"detectedBreak":{"type":"LINE_BREAK","isPrefix":false}},"boundingBox":{"vertices":[{"x":856,"y":530},{"x":881,"y":530},{"x":881,"y":612},{"x":856,"y":612}],"normalizedVertices":[]},"text":"&","confidence":0.11999999731779099}],"property":{"detectedLanguages":[{"languageCode":"fr","confidence":0}],"detectedBreak":null},"boundingBox":{"vertices":[{"x":858,"y":530},{"x":881,"y":531},{"x":879,"y":611},{"x":856,"y":611}],"normalizedVertices":[]},"confidence":0.11999999731779099}],"property":null,"boundingBox":{"vertices":[{"x":621,"y":525},{"x":881,"y":531},{"x":879,"y":612},{"x":619,"y":606}],"normalizedVertices":[]},"confidence":0.8100000023841858}],"property":null,"boundingBox":{"vertices":[{"x":621,"y":525},{"x":881,"y":531},{"x":879,"y":612},{"x":619,"y":606}],"normalizedVertices":[]},"blockType":"TEXT","confidence":0.8100000023841858},{"paragraphs":[{"words":[{"symbols":[{"property":{"detectedLanguages":[{"languageCode":"pl","confidence":0}],"detectedBreak":null},"boundingBox":{"vertices":[{"x":2,"y":1076},{"x":16,"y":1076},{"x":16,"y":1097},{"x":2,"y":1097}],"normalizedVertices":[]},"text":"o","confidence":0.8299999833106995},{"property":{"detectedLanguages":[{"languageCode":"pl","confidence":0}],"detectedBreak":{"type":"SPACE","isPrefix":false}},"boundingBox":{"vertices":[{"x":20,"y":1076},{"x":34,"y":1076},{"x":34,"y":1097},{"x":20,"y":1097}],"normalizedVertices":[]},"text":"d","confidence":0.4399999976158142}],"property":{"detectedLanguages":[{"languageCode":"pl","confidence":0}],"detectedBreak":null},"boundingBox":{"vertices":[{"x":2,"y":1076},{"x":34,"y":1076},{"x":34,"y":1097},{"x":2,"y":1097}],"normalizedVertices":[]},"confidence":0.6299999952316284},{"symbols":[{"property":{"detectedLanguages":[{"languageCode":"pl","confidence":0}],"detectedBreak":null},"boundingBox":{"vertices":[{"x":43,"y":1076},{"x":56,"y":1076},{"x":56,"y":1097},{"x":43,"y":1097}],"normalizedVertices":[]},"text":"0","confidence":0.25},{"property":{"detectedLanguages":[{"languageCode":"pl","confidence":0}],"detectedBreak":null},"boundingBox":{"vertices":[{"x":60,"y":1076},{"x":73,"y":1076},{"x":73,"y":1097},{"x":60,"y":1097}],"normalizedVertices":[]},"text":"0","confidence":0.7300000190734863},{"property":{"detectedLanguages":[{"languageCode":"pl","confidence":0}],"detectedBreak":null},"boundingBox":{"vertices":[{"x":76,"y":1076},{"x":88,"y":1076},{"x":88,"y":1097},{"x":76,"y":1097}],"normalizedVertices":[]},"text":"0","confidence":0.8600000143051147},{"property":{"detectedLanguages":[{"languageCode":"pl","confidence":0}],"detectedBreak":{"type":"LINE_BREAK","isPrefix":false}},"boundingBox":{"vertices":[{"x":93,"y":1076},{"x":107,"y":1076},{"x":107,"y":1097},{"x":93,"y":1097}],"normalizedVertices":[]},"text":"0","confidence":0.8799999952316284}],"property":{"detectedLanguages":[{"languageCode":"pl","confidence":0}],"detectedBreak":null},"boundingBox":{"vertices":[{"x":43,"y":1076},{"x":107,"y":1076},{"x":107,"y":1097},{"x":43,"y":1097}],"normalizedVertices":[]},"confidence":0.6800000071525574}],"property":null,"boundingBox":{"vertices":[{"x":2,"y":1076},{"x":107,"y":1076},{"x":107,"y":1097},{"x":2,"y":1097}],"normalizedVertices":[]},"confidence":0.6600000262260437}],"property":null,"boundingBox":{"vertices":[{"x":2,"y":1076},{"x":107,"y":1076},{"x":107,"y":1097},{"x":2,"y":1097}],"normalizedVertices":[]},"blockType":"TEXT","confidence":0.6600000262260437}],"property":{"detectedLanguages":[{"languageCode":"pl","confidence":0.550000011920929},{"languageCode":"fr","confidence":0.44999998807907104}],"detectedBreak":null},"width":1500,"height":2000,"confidence":0}],"text":"SAUF &\nod 0000\n"},"webDetection":null,"productSearchResults":null,"context":null}